{
  "$schema": "https://ui.shadcn.com/schema/registry-item.json",
  "name": "accordion-09",
  "title": "Accordion 9",
  "description": "Outline-style accordion with bordered items and spacing between each accordion item.",
  "registryDependencies": [
    "accordion"
  ],
  "files": [
    {
      "path": "src/components/shadcn-studio/accordion/accordion-09.tsx",
      "content": "import { Accordion, AccordionContent, AccordionItem, AccordionTrigger } from '@/components/ui/accordion'\n\nconst items = [\n  {\n    title: 'How do I track my order?',\n    content: `You can track your order by logging into your account and visiting the \"Orders\" section. You'll receive tracking information via email once your order ships. For real-time updates, you can also use the tracking number provided in your shipping confirmation email.`\n  },\n  {\n    title: 'What is your return policy?',\n    content:\n      'We offer a 30-day return policy for most items. Products must be unused and in their original packaging. To initiate a return, please contact our customer service team or use the return portal in your account dashboard.'\n  },\n  {\n    title: 'How can I contact customer support?',\n    content:\n      'Our customer support team is available 24/7. You can reach us via live chat, email at support@example.com, or by phone at 1-800-123-4567. For faster service, please have your order number ready when contacting us.'\n  }\n]\n\nconst AccordionOutlineDemo = () => {\n  return (\n    <Accordion type='single' collapsible className='w-full space-y-2' defaultValue='item-1'>\n      {items.map((item, index) => (\n        <AccordionItem key={index} value={`item-${index + 1}`} className='rounded-md border!'>\n          <AccordionTrigger className='px-5'>{item.title}</AccordionTrigger>\n          <AccordionContent className='text-muted-foreground px-5'>{item.content}</AccordionContent>\n        </AccordionItem>\n      ))}\n    </Accordion>\n  )\n}\n\nexport default AccordionOutlineDemo\n",
      "type": "registry:component",
      "target": "components/shadcn-studio/accordion/accordion-09.tsx"
    }
  ],
  "type": "registry:component"
}