{
  "$schema": "https://ui.shadcn.com/schema/registry-item.json",
  "name": "dialog-14",
  "title": "Dialog 14",
  "description": "Sign in dialog with gradient background and social login options",
  "dependencies": [
    "lucide-react"
  ],
  "registryDependencies": [
    "button",
    "dialog",
    "input",
    "label"
  ],
  "files": [
    {
      "path": "src/components/shadcn-studio/dialog/dialog-14.tsx",
      "content": "import { LogInIcon } from 'lucide-react'\n\nimport { Button } from '@/components/ui/button'\nimport {\n  Dialog,\n  DialogContent,\n  DialogDescription,\n  DialogFooter,\n  DialogHeader,\n  DialogTitle,\n  DialogTrigger\n} from '@/components/ui/dialog'\nimport { Input } from '@/components/ui/input'\nimport { Label } from '@/components/ui/label'\n\nconst DialogSignInDemo = () => {\n  return (\n    <Dialog>\n      <form>\n        <DialogTrigger asChild>\n          <Button variant='outline'>Sign In</Button>\n        </DialogTrigger>\n        <DialogContent className='to-card bg-gradient-to-b from-sky-100 to-40% [background-size:100%_101%] sm:max-w-sm dark:from-sky-900'>\n          <DialogHeader className='items-center'>\n            <div className='mb-4 flex size-12 items-center justify-center rounded-full bg-sky-600/10 sm:mx-0 dark:bg-sky-400/10'>\n              <LogInIcon className='size-6 text-sky-600 dark:text-sky-400' />\n            </div>\n            <DialogTitle>Sign in with email</DialogTitle>\n            <DialogDescription className='text-center'>\n              Make a new doc to bring your words, data and teams together. For free.\n            </DialogDescription>\n          </DialogHeader>\n          <form className='flex flex-col gap-4'>\n            <div className='grid gap-3'>\n              <Label htmlFor='email'>Email</Label>\n              <Input type='email' id='email' name='useremail' placeholder='example@gmail.com' />\n            </div>\n            <div className='grid gap-3'>\n              <Label htmlFor='password'>Password</Label>\n              <Input type='password' id='password' name='userpassword' placeholder='Password' />\n            </div>\n          </form>\n          <DialogFooter className='space-y-2 pt-4 sm:flex-col'>\n            <Button className='bg-sky-600 text-white hover:bg-sky-600 focus-visible:ring-sky-600 dark:bg-sky-400 dark:hover:bg-sky-400 dark:focus-visible:ring-sky-400'>\n              Get Started\n            </Button>\n            <div className='before:bg-border after:bg-border flex items-center gap-4 before:h-px before:flex-1 after:h-px after:flex-1'>\n              <span className='text-muted-foreground text-xs'>Or sign in with</span>\n            </div>\n            <div className='flex flex-wrap items-center justify-center gap-4'>\n              <Button variant='outline' className='flex-1'>\n                <img\n                  src='https://cdn.shadcnstudio.com/ss-assets/brand-logo/google-icon.png?width=20&height=20&format=auto'\n                  alt='Google Icon'\n                  className='size-5'\n                />\n              </Button>\n              <Button variant='outline' className='flex-1'>\n                <img\n                  src='https://cdn.shadcnstudio.com/ss-assets/brand-logo/twitter-icon.png?width=20&height=20&format=auto'\n                  alt='X Icon'\n                  className='size-5 dark:invert'\n                />\n              </Button>\n              <Button variant='outline' className='flex-1'>\n                <img\n                  src='https://cdn.shadcnstudio.com/ss-assets/brand-logo/facebook-icon.png?width=20&height=20&format=auto'\n                  alt='Facebook Icon'\n                  className='size-5'\n                />\n              </Button>\n              <Button variant='outline' className='flex-1'>\n                <img\n                  src='https://cdn.shadcnstudio.com/ss-assets/brand-logo/github-icon.png?width=20&height=20&format=auto'\n                  alt='GitHub Icon'\n                  className='size-5 dark:invert'\n                />\n              </Button>\n            </div>\n          </DialogFooter>\n        </DialogContent>\n      </form>\n    </Dialog>\n  )\n}\n\nexport default DialogSignInDemo\n",
      "type": "registry:component",
      "target": "components/shadcn-studio/dialog/dialog-14.tsx"
    }
  ],
  "type": "registry:component"
}