{
  "$schema": "https://ui.shadcn.com/schema/registry-item.json",
  "name": "switch-17",
  "title": "Switch 17",
  "description": "A switch card with GitHub icon for repository connection toggle functionality",
  "registryDependencies": [
    "label",
    "switch"
  ],
  "files": [
    {
      "path": "src/components/shadcn-studio/switch/switch-17.tsx",
      "content": "import { useId } from 'react'\n\nimport { Label } from '@/components/ui/label'\nimport { Switch } from '@/components/ui/switch'\n\nconst SwitchCardDemo = () => {\n  const id = useId()\n\n  return (\n    <div className='border-input has-data-[state=checked]:border-primary/50 relative flex w-full items-start gap-2 rounded-md border p-4 shadow-xs outline-none'>\n      <Switch\n        id={id}\n        className='order-1 h-4 w-6 after:absolute after:inset-0 [&_span]:size-3 data-[state=checked]:[&_span]:translate-x-2.5 data-[state=checked]:[&_span]:rtl:-translate-x-2.5'\n        aria-describedby={`${id}-description`}\n      />\n      <div className='flex grow items-center gap-3'>\n        <img\n          src='https://cdn.shadcnstudio.com/ss-assets/brand-logo/github-icon.png?width=20&height=20&format=auto'\n          alt='GitHub Icon'\n          className='size-5'\n        />\n        <div className='grid grow gap-2'>\n          <Label htmlFor={id}>Connect with GitHub</Label>\n          <p id={`${id}-description`} className='text-muted-foreground text-xs'>\n            Access your projects direct from GitHub.\n          </p>\n        </div>\n      </div>\n    </div>\n  )\n}\n\nexport default SwitchCardDemo\n",
      "type": "registry:component",
      "target": "components/shadcn-studio/switch/switch-17.tsx"
    }
  ],
  "type": "registry:component"
}